AayushUpadhyay/__init__.py
AayushUpadhyay/perceptron.py
Perceptron_Aayush007A-1.0.0.dist-info/LICENSE
Perceptron_Aayush007A-1.0.0.dist-info/METADATA
Perceptron_Aayush007A-1.0.0.dist-info/WHEEL
Perceptron_Aayush007A-1.0.0.dist-info/top_level.txt
Perceptron_Aayush007A-1.0.0.dist-info/RECORD
